file_query_text/__init__.py
file_query_text/cli.py
file_query_text/grammar.py
file_query_text/main.py
file_query_cli-0.1.0.dist-info/METADATA
file_query_cli-0.1.0.dist-info/WHEEL
file_query_cli-0.1.0.dist-info/entry_points.txt
file_query_cli-0.1.0.dist-info/top_level.txt
file_query_cli-0.1.0.dist-info/RECORD
