Metadata-Version: 2.4
Name: file_query_cli
Version: 0.1.0
Summary: SQL-like interface for querying files in your filesystem
Author-email: nik <42a11b@nikdav.is>
License-Expression: MIT
Project-URL: Homepage, https://github.com/yourusername/file-query
Project-URL: Bug Tracker, https://github.com/yourusername/file-query/issues
Classifier: Programming Language :: Python :: 3
Classifier: Operating System :: OS Independent
Requires-Python: >=3.12
Requires-Dist: pyparsing>=3.2.3
Provides-Extra: dev
Requires-Dist: pytest>=8.3.5; extra == "dev"
